lingo_fit/__init__.py
lingo_fit/api/__init__.py
lingo_fit/api/__main__.py
lingo_fit/api/endpoints/__init__.py
lingo_fit/api/endpoints/predict.py
lingo_fit/api/endpoints/train.py
lingo_fit/api/features.py
lingo_fit/api/py.typed
lingo_fit/api/recommendation_api.py
lingo_fit/api/utils.py
lingo_fit/data/__init__.py
lingo_fit/data/exercises.py
lingo_fit/data/experiences.py
lingo_fit/data/languages.py
lingo_fit/data/learners.py
lingo_fit/data/lessons.py
lingo_fit/data/progress.py
lingo_fit/data/subscriptions.py
lingo_fit/model/__init__.py
lingo_fit/model/thompson.py
lingo_fit/py.typed
lingo_fit-0.2.0.dist-info/LICENSE
lingo_fit-0.2.0.dist-info/METADATA
lingo_fit-0.2.0.dist-info/WHEEL
lingo_fit-0.2.0.dist-info/RECORD
