Metadata-Version: 2.1
Name: lingo-fit
Version: 0.2.0
Summary: 
Author: rauan_akylzhanov
Author-email: akylzhanov.r@gmail.com
Requires-Python: >=3.8.1,<3.12
Classifier: Programming Language :: Python :: 3
Classifier: Programming Language :: Python :: 3.9
Classifier: Programming Language :: Python :: 3.10
Classifier: Programming Language :: Python :: 3.11
Requires-Dist: faker (>=18.7.0,<19.0.0)
Requires-Dist: fastapi (>=0.95.1,<0.96.0)
Requires-Dist: numpy (>=1.24.3,<2.0.0)
Requires-Dist: pre-commit (>=3.3.1,<4.0.0)
Requires-Dist: pydantic (>=1.10.7,<2.0.0)
Requires-Dist: sagemaker (>=2.155.0,<3.0.0)
Requires-Dist: scipy (>=1.10.1,<2.0.0)
Requires-Dist: twine (>=4.0.2,<5.0.0)
Requires-Dist: uvicorn (>=0.22.0,<0.23.0)
